herdpy/__init__.py
herdpy/client.py
tests/__init__.py
tests/test_client.py
herdpy-0.0.6.dist-info/LICENSE
herdpy-0.0.6.dist-info/METADATA
herdpy-0.0.6.dist-info/WHEEL
herdpy-0.0.6.dist-info/top_level.txt
herdpy-0.0.6.dist-info/RECORD
