Metadata-Version: 2.1
Name: herdpy
Version: 0.0.6
Summary: Building a project herd client library
Home-page: https://github.com/istherepie/herd-python-client
Author: Steffen Park
Author-email: dev@istherepie.com
License: UNKNOWN
Project-URL: Bug Tracker, https://github.com/istherepie/herd-python-client/issues
Platform: UNKNOWN
Classifier: Programming Language :: Python :: 3
Classifier: License :: OSI Approved :: MIT License
Classifier: Operating System :: OS Independent
Requires-Python: >=3.6
Requires-Dist: requests (==2.25.1)
